torchwrapper/__init__.py
torchwrapper/wrapper.py
torchwrapper-0.0.1.dev0.dist-info/LICENSE
torchwrapper-0.0.1.dev0.dist-info/METADATA
torchwrapper-0.0.1.dev0.dist-info/WHEEL
torchwrapper-0.0.1.dev0.dist-info/top_level.txt
torchwrapper-0.0.1.dev0.dist-info/RECORD
